{
  "day_iso": "2026-06-25",
  "generated_at_utc": "2026-06-25 21:27:14 UTC",
  "generated_at_local": "2026-06-25 23:27:10 Europe/Berlin",
  "mode": "source_adapter_mvp",
  "count": 55,
  "items": [
    {
      "item_id": "stadt-kassel-aktuelles-eichenprozessionsspinner",
      "title": "Hinweise zum Eichen-prozessionsspinner",
      "summary": "Im Kasseler Stadtgebiet tritt der Eichenprozessionsspinner saisonal vermehrt an Eichen auf. Derzeit sind rund 300 städtische Eichen betroffen.",
      "source_name": "Stadt Kassel Aktuelles",
      "source_url": "https://www.kassel.de/pressemitteilungen/juni/eichenprozessionsspinner.php",
      "source_family": "official_city",
      "city": "Kassel",
      "topic": "Politics",
      "published_date": "2026-06-25",
      "summary_status": "html_adapter_minimal",
      "image_rights_status": "placeholder_default",
      "media_type": "placeholder",
      "media_url": null,
      "media_source": "local_placeholder",
      "media_rights_status": "placeholder_default",
      "image_download_allowed": false,
      "youtube_embed_allowed": true
    },
    {
      "item_id": "stadt-kassel-aktuelles-hitzefalle-auto",
      "title": "Hitze: Feuerwehr Kassel warnt vor Lebensgefahr im Auto",
      "summary": "Die Sonne scheint, ab zum Freibad, jetzt noch schnell etwas einkaufen oder kurz eine Kleinigkeit erledigen... Doch die Feuerwehr warnt dringend davor, Kinder oder Haustiere währenddessen allein im Auto zu lassen. Der.",
      "source_name": "Stadt Kassel Aktuelles",
      "source_url": "https://www.kassel.de/pressemitteilungen/juni/hitzefalle-auto.php",
      "source_family": "official_city",
      "city": "Kassel",
      "topic": "Police",
      "published_date": "2026-06-25",
      "summary_status": "html_adapter_minimal",
      "image_rights_status": "placeholder_default",
      "media_type": "placeholder",
      "media_url": null,
      "media_source": "local_placeholder",
      "media_rights_status": "placeholder_default",
      "image_download_allowed": false,
      "youtube_embed_allowed": true
    },
    {
      "item_id": "stadt-kassel-aktuelles-ortsbeirat-mitte",
      "title": "Ortsbeirat Mitte tagt am 29. Juni",
      "summary": "In der ersten Ferienwoche bestreitet der Ortsbeirat Mitte die einzige öffentliche Sitzung der städtischen Gremien.",
      "source_name": "Stadt Kassel Aktuelles",
      "source_url": "https://www.kassel.de/pressemitteilungen/juni/ortsbeirat-mitte.php",
      "source_family": "official_city",
      "city": "Kassel",
      "topic": "Politics",
      "published_date": "2026-06-25",
      "summary_status": "html_adapter_minimal",
      "image_rights_status": "placeholder_default",
      "media_type": "placeholder",
      "media_url": null,
      "media_source": "local_placeholder",
      "media_rights_status": "placeholder_default",
      "image_download_allowed": false,
      "youtube_embed_allowed": true
    },
    {
      "item_id": "landkreis-kassel-presse-ausstellung-diethart-rindermann",
      "title": "Fotografische Spurensuche in historischen Räumen",
      "summary": "Ausstellung von Diethart Rindermann zeigt Orte und Objekte zwischen Erinnerung und Gegenwart",
      "source_name": "Landkreis Kassel Pressemitteilungen",
      "source_url": "http://www.landkreiskassel.de/pressemitteilungen/juni/ausstellung-diethart-rindermann.php",
      "source_family": "official_regional",
      "city": "Kassel",
      "topic": "Politics",
      "published_date": "2026-06-25",
      "summary_status": "rss_adapter_filtered",
      "image_rights_status": "placeholder_default",
      "media_type": "placeholder",
      "media_url": null,
      "media_source": "local_placeholder",
      "media_rights_status": "placeholder_default",
      "image_download_allowed": false,
      "youtube_embed_allowed": true
    },
    {
      "item_id": "landkreis-kassel-presse-gs-grebenstein-richtfest",
      "title": "Richtfest an der Heinrich‑Grupe‑Schule",
      "summary": "Platz für Kita, Bibliothek und fünf neue Klassenräume",
      "source_name": "Landkreis Kassel Pressemitteilungen",
      "source_url": "http://www.landkreiskassel.de/pressemitteilungen/juni/gs-grebenstein-richtfest.php",
      "source_family": "official_regional",
      "city": "Kassel",
      "topic": "Politics",
      "published_date": "2026-06-24",
      "summary_status": "rss_adapter_filtered",
      "image_rights_status": "placeholder_default",
      "media_type": "placeholder",
      "media_url": null,
      "media_source": "local_placeholder",
      "media_rights_status": "placeholder_default",
      "image_download_allowed": false,
      "youtube_embed_allowed": true
    },
    {
      "item_id": "landkreis-kassel-presse-hitzetipps-haustiere",
      "title": "Vierbeiner vor Hitze schützen",
      "summary": "Fachdienst Tierschutz vom Landkreis Kassel gibt Tipps für Haus- und Nutztierbesitzer",
      "source_name": "Landkreis Kassel Pressemitteilungen",
      "source_url": "http://www.landkreiskassel.de/pressemitteilungen/juni/hitzetipps-haustiere.php",
      "source_family": "official_regional",
      "city": "Kassel",
      "topic": "Safety",
      "published_date": "2026-06-22",
      "summary_status": "rss_adapter_filtered",
      "image_rights_status": "placeholder_default",
      "media_type": "placeholder",
      "media_url": null,
      "media_source": "local_placeholder",
      "media_rights_status": "placeholder_default",
      "image_download_allowed": false,
      "youtube_embed_allowed": true
    },
    {
      "item_id": "landkreis-kassel-presse-aktionstag-kommunen-am-limit",
      "title": "Aktionstag „Kommunen am Limit“",
      "summary": "Bund und Länder müssen angesichts der kommunalen Finanzkrise endlich handeln",
      "source_name": "Landkreis Kassel Pressemitteilungen",
      "source_url": "http://www.landkreiskassel.de/pressemitteilungen/juni/aktionstag-kommunen-am-limit.php",
      "source_family": "official_regional",
      "city": "Kassel",
      "topic": "Politics",
      "published_date": "2026-06-22",
      "summary_status": "rss_adapter_filtered",
      "image_rights_status": "placeholder_default",
      "media_type": "placeholder",
      "media_url": null,
      "media_source": "local_placeholder",
      "media_rights_status": "placeholder_default",
      "image_download_allowed": false,
      "youtube_embed_allowed": true
    },
    {
      "item_id": "landkreis-kassel-presse-wohltaetigkeitskonzert-2026",
      "title": "Landkreis Kassel lädt zum Wohltätigkeitskonzert ein",
      "summary": "Am Sonntag, 28. Juni, spielt das Heeresmusikkorps Kassel wieder am Schloss Wilhelmsthal",
      "source_name": "Landkreis Kassel Pressemitteilungen",
      "source_url": "http://www.landkreiskassel.de/pressemitteilungen/juni/wohltaetigkeitskonzert-2026.php",
      "source_family": "official_regional",
      "city": "Kassel",
      "topic": "Events",
      "published_date": "2026-06-17",
      "summary_status": "rss_adapter_filtered",
      "image_rights_status": "placeholder_default",
      "media_type": "placeholder",
      "media_url": null,
      "media_source": "local_placeholder",
      "media_rights_status": "placeholder_default",
      "image_download_allowed": false,
      "youtube_embed_allowed": true
    },
    {
      "item_id": "polizei-nordhessen-presse-polizei-codierte-fahrraeder-beim-sommerfest-in-grossalmerode",
      "title": "Polizei codierte Fahrräder beim Sommerfest in Großalmerode",
      "summary": "Die Polizei blickt auf eine gelungene Präventionsaktion am vergangenen Samstag beim diesjährigen Sommerfest in Großalmerode zurück und codierte vor Ort zahlreiche Fahrräder und E-Bikes.",
      "source_name": "Polizei Nordhessen",
      "source_url": "https://www.polizei.hessen.de/meldungen/polizei-codierte-fahrraeder-beim-sommerfest-in-grossalmerode",
      "source_family": "official_police",
      "city": "Kassel",
      "topic": "Police",
      "published_date": "2026-06-15",
      "summary_status": "html_adapter_minimal",
      "image_rights_status": "placeholder_default",
      "media_type": "placeholder",
      "media_url": null,
      "media_source": "local_placeholder",
      "media_rights_status": "placeholder_default",
      "image_download_allowed": false,
      "youtube_embed_allowed": true
    },
    {
      "item_id": "polizei-nordhessen-presse-verkehrsunfallstatistik-2025-fuer-nordhessen",
      "title": "Verkehrsunfallstatistik 2025 für Nordhessen",
      "summary": "Die Zahl der polizeilich registrierten Verkehrsunfälle in Nordhessen lag im Jahr 2025 bei leichtem Rückgang in etwa auf dem Vorjahresniveau.",
      "source_name": "Polizei Nordhessen",
      "source_url": "https://www.polizei.hessen.de/meldungen/verkehrsunfallstatistik-2025-fuer-nordhessen",
      "source_family": "official_police",
      "city": "Kassel",
      "topic": "Police",
      "published_date": "2026-05-28",
      "summary_status": "html_adapter_minimal",
      "image_rights_status": "placeholder_default",
      "media_type": "placeholder",
      "media_url": null,
      "media_source": "local_placeholder",
      "media_rights_status": "placeholder_default",
      "image_download_allowed": false,
      "youtube_embed_allowed": true
    },
    {
      "item_id": "polizei-nordhessen-presse-neue-schutzleute-vor-ort-in-eschwege-und-sontra",
      "title": "Neue Schutzleute vor Ort in Eschwege und Sontra",
      "summary": "Zu einem personellen Wechsel bei der Funktion des \"Schutzmanns vor Ort\" kam es kürzlich bei den Polizeistationen in Eschwege und Sontra.",
      "source_name": "Polizei Nordhessen",
      "source_url": "https://www.polizei.hessen.de/meldungen/neue-schutzleute-vor-ort-in-eschwege-und-sontra",
      "source_family": "official_police",
      "city": "Kassel",
      "topic": "Police",
      "published_date": "2026-05-08",
      "summary_status": "html_adapter_minimal",
      "image_rights_status": "placeholder_default",
      "media_type": "placeholder",
      "media_url": null,
      "media_source": "local_placeholder",
      "media_rights_status": "placeholder_default",
      "image_download_allowed": false,
      "youtube_embed_allowed": true
    },
    {
      "item_id": "polizei-nordhessen-presse-gemeinde-herleshausen-richtet-leon-hilfe-inseln-ein",
      "title": "Gemeinde Herleshausen richtet \"Leon-Hilfe-Inseln\" ein",
      "summary": "Am vergangenen Mittwoch (15.04.) stellten Bürgermeisterin Carolin Gisselmann und Jugendkoordinator Alexander Först von der PD Werra-Meißner die insgesamt 7 neuen Leon-Hilfe-Inseln in Herleshausen vor.",
      "source_name": "Polizei Nordhessen",
      "source_url": "https://www.polizei.hessen.de/meldungen/gemeinde-herleshausen-richtet-leon-hilfe-inseln-ein",
      "source_family": "official_police",
      "city": "Kassel",
      "topic": "Police",
      "published_date": "2026-04-20",
      "summary_status": "html_adapter_minimal",
      "image_rights_status": "placeholder_default",
      "media_type": "placeholder",
      "media_url": null,
      "media_source": "local_placeholder",
      "media_rights_status": "placeholder_default",
      "image_download_allowed": false,
      "youtube_embed_allowed": true
    },
    {
      "item_id": "polizei-nordhessen-presse-cops-im-dialog-polizei-und-schule-im-austausch-an-der-bundespraesident-theodor-heuss-schule",
      "title": "\"Cops im Dialog - Polizei und Schule im Austausch\" an der Bundespräsident-Theodor-Heuss-Schule",
      "summary": "Am Montag, 17.03.2026, fand an der Bundespräsident-Theodor-Heuss-Schule in Homberg (Efze) eine weitere Veranstaltung der Dialogreihe \"Cops im Dialog - Polizei und Schule im Austausch\" statt.",
      "source_name": "Polizei Nordhessen",
      "source_url": "https://www.polizei.hessen.de/meldungen/cops-im-dialog-polizei-und-schule-im-austausch-an-der-bundespraesident-theodor-heuss-schule",
      "source_family": "official_police",
      "city": "Kassel",
      "topic": "Police",
      "published_date": "2026-03-27",
      "summary_status": "html_adapter_minimal",
      "image_rights_status": "placeholder_default",
      "media_type": "placeholder",
      "media_url": null,
      "media_source": "local_placeholder",
      "media_rights_status": "placeholder_default",
      "image_download_allowed": false,
      "youtube_embed_allowed": true
    },
    {
      "item_id": "polizei-frankfurt-presse-6302359",
      "title": "POL-F: 260625 - 0806 Frankfurt-Sachsenhausen: Vermisste Person",
      "summary": "Frankfurt (ots) - (bo) Seit gestern Abend, 24. Juni 2026 gegen 19:30 Uhr, wird der 50-jährige Herr Vadims B. aus Frankfurt Sachsenhausen vermisst. Letztmalig wurde er gestern Abend auf der Darmstädter Landstraße in.",
      "source_name": "Polizei Frankfurt Presse",
      "source_url": "https://www.presseportal.de/blaulicht/pm/4970/6302359",
      "source_family": "official_police",
      "city": "Frankfurt",
      "topic": "Transport",
      "published_date": "2026-06-25",
      "summary_status": "rss_adapter_minimal",
      "image_rights_status": "placeholder_default",
      "media_type": "placeholder",
      "media_url": null,
      "media_source": "local_placeholder",
      "media_rights_status": "placeholder_default",
      "image_download_allowed": false,
      "youtube_embed_allowed": true
    },
    {
      "item_id": "polizei-frankfurt-presse-6302240",
      "title": "POL-F: 260625 - 0805 Frankfurt-Gutleutviertel: Illegale Einfuhr von Betäubungsmitteln in nicht geringer Menge - Festnahme",
      "summary": "Frankfurt (ots) - (bo) Dienstagnacht (23. Juni 2026) nahmen Polizeibeamte einen Drogenhändler fest. Nach aktuellem Kenntnisstand meldete sich der spätere Tatverdächtige gegen 00:12 Uhr selbstständig über Notruf, da er.",
      "source_name": "Polizei Frankfurt Presse",
      "source_url": "https://www.presseportal.de/blaulicht/pm/4970/6302240",
      "source_family": "official_police",
      "city": "Frankfurt",
      "topic": "Police",
      "published_date": "2026-06-25",
      "summary_status": "rss_adapter_minimal",
      "image_rights_status": "placeholder_default",
      "media_type": "placeholder",
      "media_url": null,
      "media_source": "local_placeholder",
      "media_rights_status": "placeholder_default",
      "image_download_allowed": false,
      "youtube_embed_allowed": true
    },
    {
      "item_id": "polizei-frankfurt-presse-6302149",
      "title": "POL-F: 260625 - 0804 Frankfurt- Höchst: Jugendlicher leistet mehrfach Widerstand",
      "summary": "Frankfurt (ots) - (ma) Aufgrund einer vorangegangenen Auseinandersetzung fahndete die Polizei gestern im Bereich Höchst nach einem 17- Jährigen. Diesen erkannte eine Polizeistreife im Bereich des Höchster Bahnhofes.",
      "source_name": "Polizei Frankfurt Presse",
      "source_url": "https://www.presseportal.de/blaulicht/pm/4970/6302149",
      "source_family": "official_police",
      "city": "Frankfurt",
      "topic": "Police",
      "published_date": "2026-06-25",
      "summary_status": "rss_adapter_minimal",
      "image_rights_status": "placeholder_default",
      "media_type": "placeholder",
      "media_url": null,
      "media_source": "local_placeholder",
      "media_rights_status": "placeholder_default",
      "image_download_allowed": false,
      "youtube_embed_allowed": true
    },
    {
      "item_id": "polizei-frankfurt-presse-6302148",
      "title": "POL-F: 260625 - 0803 Frankfurt- Innenstadt/ Bahnhofsviertel: Räuber festgenommen",
      "summary": "Frankfurt (ots) - (ma) Gestern Abend (24. Juni 2026) soll ein Mann eine junge Frau überfallen haben, welche gerade in einer Bank am Roßmarkt Geld einzahlte. Er soll sie bedroht und ihr das Bargeld entrissen haben. Die.",
      "source_name": "Polizei Frankfurt Presse",
      "source_url": "https://www.presseportal.de/blaulicht/pm/4970/6302148",
      "source_family": "official_police",
      "city": "Frankfurt",
      "topic": "Police",
      "published_date": "2026-06-25",
      "summary_status": "rss_adapter_minimal",
      "image_rights_status": "placeholder_default",
      "media_type": "placeholder",
      "media_url": null,
      "media_source": "local_placeholder",
      "media_rights_status": "placeholder_default",
      "image_download_allowed": false,
      "youtube_embed_allowed": true
    },
    {
      "item_id": "polizei-frankfurt-presse-6302145",
      "title": "POL-F: 260625 - 0802 Frankfurt- Rödelheim: Schwerer Verkehrsunfall",
      "summary": "Frankfurt (ots) - (ma) Gestern Mittag (24. Juni 2026) kam es zu einem schweren Verkehrsunfall zwischen einem Fußgänger und einem Pkw in Rödelheim. Nach aktuellem Kenntnisstand soll ein 39-jähriger Fußgänger gegen 12:15.",
      "source_name": "Polizei Frankfurt Presse",
      "source_url": "https://www.presseportal.de/blaulicht/pm/4970/6302145",
      "source_family": "official_police",
      "city": "Frankfurt",
      "topic": "Transport",
      "published_date": "2026-06-25",
      "summary_status": "rss_adapter_minimal",
      "image_rights_status": "placeholder_default",
      "media_type": "placeholder",
      "media_url": null,
      "media_source": "local_placeholder",
      "media_rights_status": "placeholder_default",
      "image_download_allowed": false,
      "youtube_embed_allowed": true
    },
    {
      "item_id": "vgf-frankfurt-news-ironman-s-bahnen-und-u-bahnen-nutzen-5",
      "title": "Ironman: S-Bahnen und U-Bahnen nutzen",
      "summary": "Straßenbahnen und Busse weichen für Triathlon am 28. Juni 2026.",
      "source_name": "VGF Frankfurt News",
      "source_url": "https://www.vgf-ffm.de/de/aktuelles/news/einzelansicht/ironman-s-bahnen-und-u-bahnen-nutzen-5",
      "source_family": "public_transport",
      "city": "Frankfurt",
      "topic": "Transport",
      "published_date": "2026-06-25",
      "summary_status": "html_adapter_minimal",
      "image_rights_status": "placeholder_default",
      "media_type": "placeholder",
      "media_url": null,
      "media_source": "local_placeholder",
      "media_rights_status": "placeholder_default",
      "image_download_allowed": false,
      "youtube_embed_allowed": true
    },
    {
      "item_id": "vgf-frankfurt-news-gleis-und-weichenbau-mainzer-landstrasse",
      "title": "Gleis- und Weichenbau Mainzer Landstraße",
      "summary": "Straßenbahnlinien 11, 14 und 21 aufgrund von Gleis- und Weichenbauarbeiten im Frankfurter Westen nur eingeschränkt unterwegs.",
      "source_name": "VGF Frankfurt News",
      "source_url": "https://www.vgf-ffm.de/de/aktuelles/news/einzelansicht/gleis-und-weichenbau-mainzer-landstrasse",
      "source_family": "public_transport",
      "city": "Frankfurt",
      "topic": "Transport",
      "published_date": "2026-06-23",
      "summary_status": "html_adapter_minimal",
      "image_rights_status": "placeholder_default",
      "media_type": "placeholder",
      "media_url": null,
      "media_source": "local_placeholder",
      "media_rights_status": "placeholder_default",
      "image_download_allowed": false,
      "youtube_embed_allowed": true
    },
    {
      "item_id": "vgf-frankfurt-news-sicher-unterwegs-2",
      "title": "„Sicher unterwegs“",
      "summary": "VGF setzt Informations-Veranstaltungen rund um die Sicherheit fort – Zwei Termine im Juni.",
      "source_name": "VGF Frankfurt News",
      "source_url": "https://www.vgf-ffm.de/de/aktuelles/news/einzelansicht/sicher-unterwegs-2",
      "source_family": "public_transport",
      "city": "Frankfurt",
      "topic": "Safety",
      "published_date": "2026-06-16",
      "summary_status": "html_adapter_minimal",
      "image_rights_status": "placeholder_default",
      "media_type": "placeholder",
      "media_url": null,
      "media_source": "local_placeholder",
      "media_rights_status": "placeholder_default",
      "image_download_allowed": false,
      "youtube_embed_allowed": true
    },
    {
      "item_id": "vgf-frankfurt-news-aufzugs-nachruestung-beginnt",
      "title": "Aufzugs-Nachrüstung beginnt",
      "summary": "U-Bahn-Stationen \"Niddapark\" und \"Römerstadt\" werden barrierefrei",
      "source_name": "VGF Frankfurt News",
      "source_url": "https://www.vgf-ffm.de/de/aktuelles/news/einzelansicht/aufzugs-nachruestung-beginnt",
      "source_family": "public_transport",
      "city": "Frankfurt",
      "topic": "Transport",
      "published_date": "2026-06-11",
      "summary_status": "html_adapter_minimal",
      "image_rights_status": "placeholder_default",
      "media_type": "placeholder",
      "media_url": null,
      "media_source": "local_placeholder",
      "media_rights_status": "placeholder_default",
      "image_download_allowed": false,
      "youtube_embed_allowed": true
    },
    {
      "item_id": "vgf-frankfurt-news-fussball-wm-mit-bahnen-und-bussen-sicher-nach-hause-die-ganze-nacht-hindurch",
      "title": "Fußball-WM: Mit Bahnen und Bussen sicher nach Hause die ganze Nacht hindurch",
      "summary": "Fans dank 24-Stunden-Angebot mit U-Bahnen, Trams und Metrobussen auch bei späten Partien bestens bedient.",
      "source_name": "VGF Frankfurt News",
      "source_url": "https://www.vgf-ffm.de/de/aktuelles/news/einzelansicht/fussball-wm-mit-bahnen-und-bussen-sicher-nach-hause-die-ganze-nacht-hindurch",
      "source_family": "public_transport",
      "city": "Frankfurt",
      "topic": "Transport",
      "published_date": "2026-06-10",
      "summary_status": "html_adapter_minimal",
      "image_rights_status": "placeholder_default",
      "media_type": "placeholder",
      "media_url": null,
      "media_source": "local_placeholder",
      "media_rights_status": "placeholder_default",
      "image_download_allowed": false,
      "youtube_embed_allowed": true
    },
    {
      "item_id": "mainova-frankfurt-presse-fernwaermeausbau-in-der-frankenallee-geht-weiter-169972",
      "title": "Fernwärmeausbau in der Frankenallee geht weiter",
      "summary": "Der Fernwärme-Ausbau in der Frankenallee wird fortgesetzt.",
      "source_name": "Mainova Frankfurt Presse",
      "source_url": "https://www.mainova.de/de/ihre-mainova/presse/pressemitteilungen/2026/fernwaermeausbau-in-der-frankenallee-geht-weiter-169972",
      "source_family": "official_energy",
      "city": "Frankfurt",
      "topic": "Transport",
      "published_date": "2026-06-25",
      "summary_status": "html_adapter_minimal",
      "image_rights_status": "placeholder_default",
      "media_type": "placeholder",
      "media_url": null,
      "media_source": "local_placeholder",
      "media_rights_status": "placeholder_default",
      "image_download_allowed": false,
      "youtube_embed_allowed": true
    },
    {
      "item_id": "mainova-frankfurt-presse-trinkwasserpreis-steigt-leicht-169168",
      "title": "Trinkwasserpreis steigt leicht",
      "summary": "Unter anderem aufgrund höherer Bezugskosten steigt der Trinkwasserpreis leicht zum 1. Juli.",
      "source_name": "Mainova Frankfurt Presse",
      "source_url": "https://www.mainova.de/de/ihre-mainova/presse/pressemitteilungen/2026/trinkwasserpreis-steigt-leicht-169168",
      "source_family": "official_energy",
      "city": "Frankfurt",
      "topic": "Economy",
      "published_date": "2026-06-16",
      "summary_status": "html_adapter_minimal",
      "image_rights_status": "placeholder_default",
      "media_type": "placeholder",
      "media_url": null,
      "media_source": "local_placeholder",
      "media_rights_status": "placeholder_default",
      "image_download_allowed": false,
      "youtube_embed_allowed": true
    },
    {
      "item_id": "mainova-frankfurt-presse-mainova-setzt-inbetriebnahme-des-vorbildkraftwerks-fort-169094",
      "title": "Mainova setzt Inbetriebnahme des Vorbildkraftwerks fort",
      "summary": "Nach den erfolgreichen Testläufen der beiden leistungsstarken Gasturbinen folgen die nächsten Schritte der laufenden Inbetriebnahme des wasserstofffähigen Vorbildkraftwerks.",
      "source_name": "Mainova Frankfurt Presse",
      "source_url": "https://www.mainova.de/de/ihre-mainova/presse/pressemitteilungen/2026/mainova-setzt-inbetriebnahme-des-vorbildkraftwerks-fort-169094",
      "source_family": "official_energy",
      "city": "Frankfurt",
      "topic": "Economy",
      "published_date": "2026-06-11",
      "summary_status": "html_adapter_minimal",
      "image_rights_status": "placeholder_default",
      "media_type": "placeholder",
      "media_url": null,
      "media_source": "local_placeholder",
      "media_rights_status": "placeholder_default",
      "image_download_allowed": false,
      "youtube_embed_allowed": true
    },
    {
      "item_id": "mainova-frankfurt-presse-teilrueckbau-des-sarotti-schornsteins-startet-169022",
      "title": "Teilrückbau des Sarotti-Schornsteins startet",
      "summary": "Ende Juni 2026 beginnt der Teilrückbau des Schornsteins der ehemaligen Sarotti-Fabrik in Hattersheim",
      "source_name": "Mainova Frankfurt Presse",
      "source_url": "https://www.mainova.de/de/ihre-mainova/presse/pressemitteilungen/2026/teilrueckbau-des-sarotti-schornsteins-startet-169022",
      "source_family": "official_energy",
      "city": "Frankfurt",
      "topic": "Transport",
      "published_date": "2026-06-09",
      "summary_status": "html_adapter_minimal",
      "image_rights_status": "placeholder_default",
      "media_type": "placeholder",
      "media_url": null,
      "media_source": "local_placeholder",
      "media_rights_status": "placeholder_default",
      "image_download_allowed": false,
      "youtube_embed_allowed": true
    },
    {
      "item_id": "mainova-frankfurt-presse-fernwaermeausbau-in-der-bockenheimer-landstrasse-startet-168614",
      "title": "Fernwärmeausbau in der Bockenheimer Landstraße startet",
      "summary": "In der Bockenheimer Landstraße beginnt in Kürze der Ausbau der klimaschonenden Fernwärme. Die Arbeiten am Stromnetz werden ebenfalls fortgesetzt.",
      "source_name": "Mainova Frankfurt Presse",
      "source_url": "https://www.mainova.de/de/ihre-mainova/presse/pressemitteilungen/2026/fernwaermeausbau-in-der-bockenheimer-landstrasse-startet-168614",
      "source_family": "official_energy",
      "city": "Frankfurt",
      "topic": "Transport",
      "published_date": "2026-05-29",
      "summary_status": "html_adapter_minimal",
      "image_rights_status": "placeholder_default",
      "media_type": "placeholder",
      "media_url": null,
      "media_source": "local_placeholder",
      "media_rights_status": "placeholder_default",
      "image_download_allowed": false,
      "youtube_embed_allowed": true
    },
    {
      "item_id": "stadt-wiesbaden-presse-einspurige-verkehrsfuehrung-auf-konrad-adenauer-ring-zwischen-biebricher-allee-und-steinberger-strasse",
      "title": "Einspurige Verkehrsführung auf Konrad-Adenauer-Ring zwischen Biebricher Allee und Steinberger Straße",
      "summary": "Wegen der Erneuerung von Kanälen im Auftrag der Entsorgungsbetriebe (ELW) kommt es ab Montag, 29. Juni, auf dem Konrad-Adenauer-Ring zwischen Biebricher Allee und Steinberger Straße zu Verkehrsbeschränkungen.",
      "source_name": "Landeshauptstadt Wiesbaden Presse",
      "source_url": "https://www.wiesbaden.de/pressemitteilungen/pressereferat/juni/einspurige-verkehrsfuehrung-auf-konrad-adenauer-ring-zwischen-biebricher-allee-und-steinberger-strasse",
      "source_family": "official_city",
      "city": "Wiesbaden",
      "topic": "Transport",
      "published_date": "2026-06-25",
      "summary_status": "rss_adapter_minimal",
      "image_rights_status": "placeholder_default",
      "media_type": "placeholder",
      "media_url": null,
      "media_source": "local_placeholder",
      "media_rights_status": "placeholder_default",
      "image_download_allowed": false,
      "youtube_embed_allowed": true
    },
    {
      "item_id": "stadt-wiesbaden-presse-arbeiten-in-schiersteiner-strasse-drei-massnahmen-eine-baustelle",
      "title": "Arbeiten in Schiersteiner Straße Höhe Waldstraße: Drei Maßnahmen, eine Baustelle",
      "summary": "Aufgrund mehrerer notwendigen Baumaßnahmen kommt es ab Ende Juni in der Schiersteiner Straße im Abschnitt zwischen der Saarstraße und dem Einmündungsbereich der Waldstraße zu Verkehrsbeschränkungen. Durch eine.",
      "source_name": "Landeshauptstadt Wiesbaden Presse",
      "source_url": "https://www.wiesbaden.de/pressemitteilungen/pressereferat/juni/arbeiten-in-schiersteiner-strasse-drei-massnahmen-eine-baustelle",
      "source_family": "official_city",
      "city": "Wiesbaden",
      "topic": "Transport",
      "published_date": "2026-06-25",
      "summary_status": "rss_adapter_minimal",
      "image_rights_status": "placeholder_default",
      "media_type": "placeholder",
      "media_url": null,
      "media_source": "local_placeholder",
      "media_rights_status": "placeholder_default",
      "image_download_allowed": false,
      "youtube_embed_allowed": true
    },
    {
      "item_id": "stadt-wiesbaden-presse-tier-und-pflanzenpark-fasanerie-verkuerzt-geoeffnet",
      "title": "Tier- und Pflanzenpark Fasanerie verkürzt geöffnet",
      "summary": "Der Tier- und Pflanzenpark Fasanerie, Wilfried-Ries-Straße 22, ist am Freitag, 26. Juni, und am Samstag, 27. Juni, nur von 9 bis 12 Uhr geöffnet. Der Deutsche Wetterdienst hat für beide Tage eine Hitzewarnung.",
      "source_name": "Landeshauptstadt Wiesbaden Presse",
      "source_url": "https://www.wiesbaden.de/pressemitteilungen/pressereferat/juni/tier-und-pflanzenpark-fasanerie-verkuerzt-geoeffnet",
      "source_family": "official_city",
      "city": "Wiesbaden",
      "topic": "Transport",
      "published_date": "2026-06-25",
      "summary_status": "rss_adapter_minimal",
      "image_rights_status": "placeholder_default",
      "media_type": "placeholder",
      "media_url": null,
      "media_source": "local_placeholder",
      "media_rights_status": "placeholder_default",
      "image_download_allowed": false,
      "youtube_embed_allowed": true
    },
    {
      "item_id": "stadt-wiesbaden-presse-neugasse-verkehrseinschraenkungen-wegen-erneuerung-einer-versorgungsleitung",
      "title": "Neugasse: Verkehrseinschränkungen wegen Erneuerung einer Versorgungsleitung",
      "summary": "ESWE Versorgung erneuert aktuell ein längeres Teilstück der Versorgungsleitung in der Neugasse. Durch die Bauarbeiten kommt es zu Verkehrseinschränkungen. Ziel der Maßnahme ist es, die Versorgungssicherheit langfristig.",
      "source_name": "Landeshauptstadt Wiesbaden Presse",
      "source_url": "https://www.wiesbaden.de/pressemitteilungen/pressereferat/juni/neugasse-verkehrseinschraenkungen-wegen-erneuerung-einer-versorgungsleitung",
      "source_family": "official_city",
      "city": "Wiesbaden",
      "topic": "Transport",
      "published_date": "2026-06-25",
      "summary_status": "rss_adapter_minimal",
      "image_rights_status": "placeholder_default",
      "media_type": "placeholder",
      "media_url": null,
      "media_source": "local_placeholder",
      "media_rights_status": "placeholder_default",
      "image_download_allowed": false,
      "youtube_embed_allowed": true
    },
    {
      "item_id": "stadt-wiesbaden-presse-eiskalte-geschaefte-vortrag-im-stadtmuseum",
      "title": "„Eiskalte Geschäfte“: Vortrag im Stadtarchiv",
      "summary": "Am Dienstag, 30. Juni, hält der Technikjournalist Peter Thomas um 18 Uhr im Stadtarchiv Wiesbaden, Im Rad 42, einen Vortrag zum Thema „Eiskalte Geschäfte: Carl von Linde und der Siegeszug der künstlichen Kälte“. Um.",
      "source_name": "Landeshauptstadt Wiesbaden Presse",
      "source_url": "https://www.wiesbaden.de/pressemitteilungen/pressereferat/juni/eiskalte-geschaefte-vortrag-im-stadtmuseum",
      "source_family": "official_city",
      "city": "Wiesbaden",
      "topic": "Events",
      "published_date": "2026-06-25",
      "summary_status": "rss_adapter_minimal",
      "image_rights_status": "placeholder_default",
      "media_type": "placeholder",
      "media_url": null,
      "media_source": "local_placeholder",
      "media_rights_status": "placeholder_default",
      "image_download_allowed": false,
      "youtube_embed_allowed": true
    },
    {
      "item_id": "polizei-wiesbaden-presse-6302313",
      "title": "POL-WI: Keine presserelevanten Sachverhalte",
      "summary": "Wiesbaden (ots) - Keine presserelevanten Sachverhalte, Wiesbaden, Donnerstag, 25.06.2026 (kq)Für den Zuständigkeitsbereich der Polizeidirektion Wiesbaden liegen heute keine presserelevanten Sachverhalte vor. Rückfragen.",
      "source_name": "Polizei Wiesbaden Presse",
      "source_url": "https://www.presseportal.de/blaulicht/pm/43562/6302313",
      "source_family": "official_police",
      "city": "Wiesbaden",
      "topic": "Police",
      "published_date": "2026-06-25",
      "summary_status": "rss_adapter_minimal",
      "image_rights_status": "placeholder_default",
      "media_type": "placeholder",
      "media_url": null,
      "media_source": "local_placeholder",
      "media_rights_status": "placeholder_default",
      "image_download_allowed": false,
      "youtube_embed_allowed": true
    },
    {
      "item_id": "polizei-wiesbaden-presse-6301407",
      "title": "BKA: Operation Endgame mit weiterem Erfolg: Drei gefährliche Schadsoftware-Varianten vom Netz genommen",
      "summary": "Wiesbaden (ots) - Rund 15.000 Webseiten, über 320 Server und mehr als 140 Domains unschädlich gemacht +++ Ca. 27 Millionen Opferdaten sichergestellt +++ Erfolgreiche Zusammenarbeit mit Kooperationspartnern aus der.",
      "source_name": "Polizei Wiesbaden Presse",
      "source_url": "https://www.presseportal.de/blaulicht/pm/7/6301407",
      "source_family": "official_police",
      "city": "Wiesbaden",
      "topic": "Police",
      "published_date": "2026-06-24",
      "summary_status": "rss_adapter_minimal",
      "image_rights_status": "placeholder_default",
      "media_type": "placeholder",
      "media_url": null,
      "media_source": "local_placeholder",
      "media_rights_status": "placeholder_default",
      "image_download_allowed": false,
      "youtube_embed_allowed": true
    },
    {
      "item_id": "polizei-wiesbaden-presse-6301406",
      "title": "LKA-HE: Schusswaffengebrauch nach Angriff - Polizeibeamter leicht verletzt, Angreifer schwer verletzt",
      "summary": "Wiesbaden / Frankfurt (ots) - Gemeinsame Folge-Pressemitteilung der Staatsanwaltschaft Frankfurt am Main und des Hessischen Landeskriminalamts (HLKA) Am Dienstagnachmittag (23.06.) kam es gegen 16:00 Uhr am Frankfurter.",
      "source_name": "Polizei Wiesbaden Presse",
      "source_url": "https://www.presseportal.de/blaulicht/pm/43563/6301406",
      "source_family": "official_police",
      "city": "Wiesbaden",
      "topic": "Police",
      "published_date": "2026-06-24",
      "summary_status": "rss_adapter_minimal",
      "image_rights_status": "placeholder_default",
      "media_type": "placeholder",
      "media_url": null,
      "media_source": "local_placeholder",
      "media_rights_status": "placeholder_default",
      "image_download_allowed": false,
      "youtube_embed_allowed": true
    },
    {
      "item_id": "polizei-wiesbaden-presse-6301212",
      "title": "POL-WI: Hochwertige Rolex bei Juwelier gestohlen +++ Trickdiebstahl auf Parkplatz eines Einkaufsgeschäftes +++ Motorradfahrer bei Verkehrsunfall schwer verletzt",
      "summary": "Wiesbaden (ots) - 1. Hochwertige Rolex bei Juwelier gestohlen, Wiesbaden-Mitte, Wilhelmstraße Dienstag, 23.06.2026, 15:45 Uhr (kq)Am Montagnachmittag entwendeten zwei bislang unbekannte Täter in einem Juweliergeschäft.",
      "source_name": "Polizei Wiesbaden Presse",
      "source_url": "https://www.presseportal.de/blaulicht/pm/43562/6301212",
      "source_family": "official_police",
      "city": "Wiesbaden",
      "topic": "Transport",
      "published_date": "2026-06-24",
      "summary_status": "rss_adapter_minimal",
      "image_rights_status": "placeholder_default",
      "media_type": "placeholder",
      "media_url": null,
      "media_source": "local_placeholder",
      "media_rights_status": "placeholder_default",
      "image_download_allowed": false,
      "youtube_embed_allowed": true
    },
    {
      "item_id": "polizei-wiesbaden-presse-6300997",
      "title": "POL-WI-KvD: +++Rücknahme der Fahndung nach der 90-jährigen Frau aus Wiesbaden+++",
      "summary": "Wiesbaden (ots) - (jul) Die Öffentlichkeitsfahndung nach der vermissten 90-jährigen Frau aus Wiesbaden von Mittwoch, 24.06.2026 um 01:51 Uhr wird hiermit zurückgenommen. Die Frau konnte wohlbehalten angetroffen werden.",
      "source_name": "Polizei Wiesbaden Presse",
      "source_url": "https://www.presseportal.de/blaulicht/pm/11815/6300997",
      "source_family": "official_police",
      "city": "Wiesbaden",
      "topic": "Police",
      "published_date": "2026-06-24",
      "summary_status": "rss_adapter_minimal",
      "image_rights_status": "placeholder_default",
      "media_type": "placeholder",
      "media_url": null,
      "media_source": "local_placeholder",
      "media_rights_status": "placeholder_default",
      "image_download_allowed": false,
      "youtube_embed_allowed": true
    },
    {
      "item_id": "stadt-darmstadt-presse-ermaessigter-eintritt-im-nordbad-fuer-woog-saisonkarteninhaber",
      "title": "Woog",
      "summary": "Ermäßigter Eintritt im Nordbad für Woog-Saisonkarteninhaber für die Dauer der Woog-Schließung.",
      "source_name": "Wissenschaftsstadt Darmstadt Presse",
      "source_url": "https://www.darmstadt.de/presseportal/pressemitteilungen/einzelansicht/ermaessigter-eintritt-im-nordbad-fuer-woog-saisonkarteninhaber",
      "source_family": "official_city",
      "city": "Darmstadt",
      "topic": "Politics",
      "published_date": "2026-06-25",
      "summary_status": "html_adapter_minimal",
      "image_rights_status": "placeholder_default",
      "media_type": "placeholder",
      "media_url": null,
      "media_source": "local_placeholder",
      "media_rights_status": "placeholder_default",
      "image_download_allowed": false,
      "youtube_embed_allowed": true
    },
    {
      "item_id": "stadt-darmstadt-presse-hitze-und-trockenheit",
      "title": "Hitze und Trockenheit",
      "summary": "Wissenschaftsstadt Darmstadt warnt vor Waldbrandgefahr",
      "source_name": "Wissenschaftsstadt Darmstadt Presse",
      "source_url": "https://www.darmstadt.de/presseportal/pressemitteilungen/einzelansicht/hitze-und-trockenheit",
      "source_family": "official_city",
      "city": "Darmstadt",
      "topic": "Safety",
      "published_date": "2026-06-25",
      "summary_status": "html_adapter_minimal",
      "image_rights_status": "placeholder_default",
      "media_type": "placeholder",
      "media_url": null,
      "media_source": "local_placeholder",
      "media_rights_status": "placeholder_default",
      "image_download_allowed": false,
      "youtube_embed_allowed": true
    },
    {
      "item_id": "polizei-darmstadt-presse-6302224",
      "title": "POL-DA: Darmstadt-Eberstadt: Motorroller (DA-B 178) gestohlen / Zeugen gesucht",
      "summary": "Darmstadt (ots) - Unbekannte entwendeten zwischen Mittwochabend (24.6.) und Donnerstagmorgen (25.6.) einen in der Arndtstraße abgestellten grauen Motorroller (Leichtkraftrad) der Marke SYM mit dem Kennzeichen DA-B 178.",
      "source_name": "Polizei Darmstadt Presse",
      "source_url": "https://www.presseportal.de/blaulicht/pm/4969/6302224",
      "source_family": "official_police",
      "city": "Darmstadt",
      "topic": "Police",
      "published_date": "2026-06-25",
      "summary_status": "rss_adapter_minimal",
      "image_rights_status": "placeholder_default",
      "media_type": "placeholder",
      "media_url": null,
      "media_source": "local_placeholder",
      "media_rights_status": "placeholder_default",
      "image_download_allowed": false,
      "youtube_embed_allowed": true
    },
    {
      "item_id": "polizei-darmstadt-presse-6301652",
      "title": "POL-DA: Darmstadt: Zeugen nach Verkehrsunfallflucht gesucht / 11-Jähriger leicht verletzt",
      "summary": "Darmstadt (ots) - Am Mittwochmorgen (24.6.) gegen 07:30 Uhr, kam es an der Kreuzung Groß-Gerauer Weg / Eschollbrücker Straße zu einem Verkehrsunfall, bei dem ein 11-jähriger Junge leicht verletzt wurde. Nach ersten.",
      "source_name": "Polizei Darmstadt Presse",
      "source_url": "https://www.presseportal.de/blaulicht/pm/4969/6301652",
      "source_family": "official_police",
      "city": "Darmstadt",
      "topic": "Police",
      "published_date": "2026-06-25",
      "summary_status": "rss_adapter_minimal",
      "image_rights_status": "placeholder_default",
      "media_type": "placeholder",
      "media_url": null,
      "media_source": "local_placeholder",
      "media_rights_status": "placeholder_default",
      "image_download_allowed": false,
      "youtube_embed_allowed": true
    },
    {
      "item_id": "polizei-darmstadt-presse-6301087",
      "title": "POL-DA: Darmstadt: Polizei sucht rechtmäßigen Fahrradeigentümer",
      "summary": "Darmstadt (ots) - Nach der Sicherstellung eines mutmaßlich gestohlenen Fahrrads sucht die Polizei jetzt nach dem rechtmäßigen Eigentümer. Am 23. Juni 2026 stellten die Beamten ein schwarz-rotes E-Bike (Klapprad) der.",
      "source_name": "Polizei Darmstadt Presse",
      "source_url": "https://www.presseportal.de/blaulicht/pm/4969/6301087",
      "source_family": "official_police",
      "city": "Darmstadt",
      "topic": "Police",
      "published_date": "2026-06-24",
      "summary_status": "rss_adapter_minimal",
      "image_rights_status": "placeholder_default",
      "media_type": "placeholder",
      "media_url": null,
      "media_source": "local_placeholder",
      "media_rights_status": "placeholder_default",
      "image_download_allowed": false,
      "youtube_embed_allowed": true
    },
    {
      "item_id": "polizei-darmstadt-presse-6301065",
      "title": "POL-DA: Darmstadt: Umfangreiche Kontrollen im Rahmen \"Sichere Innenstadt\" / Rauschgift, Handtaschen und Fahrräder sichergestellt",
      "summary": "Darmstadt (ots) - Im Rahmen der Innenstadtoffensive \"Sichere Innenstadt\" führten Beamtinnen und Beamte des Polizeipräsidiums Südhessen am Dienstag (23.6.), unterstützt von Einsatzkräften der Hessischen.",
      "source_name": "Polizei Darmstadt Presse",
      "source_url": "https://www.presseportal.de/blaulicht/pm/4969/6301065",
      "source_family": "official_police",
      "city": "Darmstadt",
      "topic": "Police",
      "published_date": "2026-06-24",
      "summary_status": "rss_adapter_minimal",
      "image_rights_status": "placeholder_default",
      "media_type": "placeholder",
      "media_url": null,
      "media_source": "local_placeholder",
      "media_rights_status": "placeholder_default",
      "image_download_allowed": false,
      "youtube_embed_allowed": true
    },
    {
      "item_id": "polizei-darmstadt-presse-6300890",
      "title": "POL-DA: Darmstadt-Arheilgen: Einbruch in Schwimmbadkiosk / Wer kann Hinweise geben?",
      "summary": "Darmstadt (ots) - Bislang unbekannte Täter brachen zwischen Montagabend (22.6.), gegen 20 Uhr, und Dienstagmorgen (23.6.), gegen 06.45 Uhr, in einen Kiosk eines Badesees im Brücherweg ein. Nach derzeitigem.",
      "source_name": "Polizei Darmstadt Presse",
      "source_url": "https://www.presseportal.de/blaulicht/pm/4969/6300890",
      "source_family": "official_police",
      "city": "Darmstadt",
      "topic": "Police",
      "published_date": "2026-06-24",
      "summary_status": "rss_adapter_minimal",
      "image_rights_status": "placeholder_default",
      "media_type": "placeholder",
      "media_url": null,
      "media_source": "local_placeholder",
      "media_rights_status": "placeholder_default",
      "image_download_allowed": false,
      "youtube_embed_allowed": true
    },
    {
      "item_id": "hessen-economy-transport-presse-600-millionen-projekt-staerkt-frankfurts-position-als-europas-fuehrendes-luftfrachtdrehkreuz",
      "title": "600-Millionen-Projekt stärkt Frankfurts Position als Europas führendes Luftfrachtdrehkreuz",
      "summary": "Die Modernisierung erfolgt auf einer Fläche von rund 80.000 Quadratmetern und während des laufenden Betriebs.",
      "source_name": "Hessen Wirtschaft und Verkehr Presse",
      "source_url": "https://wirtschaft.hessen.de/presse/600-millionen-projekt-staerkt-frankfurts-position-als-europas-fuehrendes-luftfrachtdrehkreuz",
      "source_family": "official_state",
      "city": "Hessen",
      "topic": "Transport",
      "published_date": "2026-06-25",
      "summary_status": "html_adapter_minimal",
      "image_rights_status": "placeholder_default",
      "media_type": "placeholder",
      "media_url": null,
      "media_source": "local_placeholder",
      "media_rights_status": "placeholder_default",
      "image_download_allowed": false,
      "youtube_embed_allowed": true
    },
    {
      "item_id": "hessen-economy-transport-presse-wirtschaftsminister-mansoori-uebergibt-foerderbescheid-fuer-innovatives-recyclingverfahren-bei",
      "title": "Wirtschaftsminister Mansoori übergibt Förderbescheid für innovatives Recyclingverfahren bei Evonik",
      "summary": "Mit der Förderung unterstützt das Land Hessen die Weiterentwicklung eines innovativen Verfahrens zum Recycling von Polyurethan-Schaum.",
      "source_name": "Hessen Wirtschaft und Verkehr Presse",
      "source_url": "https://wirtschaft.hessen.de/presse/wirtschaftsminister-mansoori-uebergibt-foerderbescheid-fuer-innovatives-recyclingverfahren-bei",
      "source_family": "official_state",
      "city": "Hessen",
      "topic": "Transport",
      "published_date": "2026-06-25",
      "summary_status": "html_adapter_minimal",
      "image_rights_status": "placeholder_default",
      "media_type": "placeholder",
      "media_url": null,
      "media_source": "local_placeholder",
      "media_rights_status": "placeholder_default",
      "image_download_allowed": false,
      "youtube_embed_allowed": true
    },
    {
      "item_id": "hessen-economy-transport-presse-verlaengerung-der-mischuv-war-richtige-uebergangsloesung-ministerium-beantwortet-wichtige-fragen",
      "title": "Verlängerung der MiSchuV war richtige Übergangslösung: Ministerium beantwortet wichtige Fragen",
      "summary": "Die Verlängerung der Mieterschutzverordnung im November 2025 war aus Sicht der Landesregierung eine notwendige Übergangslösung im Interesse der Mieterinnen und Mieter.",
      "source_name": "Hessen Wirtschaft und Verkehr Presse",
      "source_url": "https://wirtschaft.hessen.de/presse/verlaengerung-der-mischuv-war-richtige-uebergangsloesung-ministerium-beantwortet-wichtige-fragen",
      "source_family": "official_state",
      "city": "Hessen",
      "topic": "Transport",
      "published_date": "2026-06-24",
      "summary_status": "html_adapter_minimal",
      "image_rights_status": "placeholder_default",
      "media_type": "placeholder",
      "media_url": null,
      "media_source": "local_placeholder",
      "media_rights_status": "placeholder_default",
      "image_download_allowed": false,
      "youtube_embed_allowed": true
    },
    {
      "item_id": "hessen-economy-transport-presse-gemeinsame-erklaerung-zur-staerkung-der-giesserei-industrie",
      "title": "Gemeinsame Erklärung zur Stärkung der Gießerei-Industrie",
      "summary": "Im Mittelpunkt stand die Wettbewerbsfähigkeit des Industriestandorts Deutschland, die Transformation hin zur Klimaneutralität sowie die Sicherung von Wertschöpfung und Beschäftigung in Hessen.",
      "source_name": "Hessen Wirtschaft und Verkehr Presse",
      "source_url": "https://wirtschaft.hessen.de/presse/gemeinsame-erklaerung-zur-staerkung-der-giesserei-industrie",
      "source_family": "official_state",
      "city": "Hessen",
      "topic": "Safety",
      "published_date": "2026-06-24",
      "summary_status": "html_adapter_minimal",
      "image_rights_status": "placeholder_default",
      "media_type": "placeholder",
      "media_url": null,
      "media_source": "local_placeholder",
      "media_rights_status": "placeholder_default",
      "image_download_allowed": false,
      "youtube_embed_allowed": true
    },
    {
      "item_id": "hessen-economy-transport-presse-minister-mansoori-verleiht-active2work-awards-2026",
      "title": "Minister Mansoori verleiht active2work Awards 2026",
      "summary": "Die Preisträgerunternehmen Baugesellschaft Hanau GmbH aus Hanau und die Schlosserei Marlis von Kessler aus Frankfurt nahmen die Auszeichnung auf der EUROBIKE in Frankfurt am Main entgegen.",
      "source_name": "Hessen Wirtschaft und Verkehr Presse",
      "source_url": "https://wirtschaft.hessen.de/presse/minister-mansoori-verleiht-active2work-awards-2026",
      "source_family": "official_state",
      "city": "Hessen",
      "topic": "Transport",
      "published_date": "2026-06-24",
      "summary_status": "html_adapter_minimal",
      "image_rights_status": "placeholder_default",
      "media_type": "placeholder",
      "media_url": null,
      "media_source": "local_placeholder",
      "media_rights_status": "placeholder_default",
      "image_download_allowed": false,
      "youtube_embed_allowed": true
    },
    {
      "item_id": "hessen-government-presse-forstministerium-weist-auf-waldbrandgefahr-hin",
      "title": "Forstministerium weist auf Waldbrandgefahr hin",
      "summary": "Es werden alle Besucher, insbesondere mit Blick auf die aktuell intensive Freizeitnutzung im Wald, um erhöhte Vorsicht und Aufmerksamkeit gebeten.",
      "source_name": "Hessische Landesregierung Presse",
      "source_url": "https://www.hessen.de/presse/forstministerium-weist-auf-waldbrandgefahr-hin",
      "source_family": "official_state",
      "city": "Hessen",
      "topic": "Politics",
      "published_date": "2026-06-25",
      "summary_status": "html_adapter_minimal",
      "image_rights_status": "placeholder_default",
      "media_type": "placeholder",
      "media_url": null,
      "media_source": "local_placeholder",
      "media_rights_status": "placeholder_default",
      "image_download_allowed": false,
      "youtube_embed_allowed": true
    },
    {
      "item_id": "hessen-government-presse-das-land-fuehrt-kostenlose-schwimmkurse-fuer-kinder-und-jugendliche-fort",
      "title": "Land führt kostenlose Schwimmkurse für Kinder und Jugendliche fort",
      "summary": "Im vergangenen Jahr konnten über 1.200 Kindern und Jugendlichen mithilfe kostenloser Schwimmkurse wichtige Schwimmfähigkeiten vermittelt werden.",
      "source_name": "Hessische Landesregierung Presse",
      "source_url": "https://www.hessen.de/presse/das-land-fuehrt-kostenlose-schwimmkurse-fuer-kinder-und-jugendliche-fort",
      "source_family": "official_state",
      "city": "Hessen",
      "topic": "Politics",
      "published_date": "2026-06-25",
      "summary_status": "html_adapter_minimal",
      "image_rights_status": "placeholder_default",
      "media_type": "placeholder",
      "media_url": null,
      "media_source": "local_placeholder",
      "media_rights_status": "placeholder_default",
      "image_download_allowed": false,
      "youtube_embed_allowed": true
    },
    {
      "item_id": "hessen-government-presse-hessen-setzt-auf-die-foerderung-junger-forschungs-talente-und-wissenschaftliche-neugier",
      "title": "„Hessen setzt auf die Förderung junger Forschungs-Talente und wissenschaftliche Neugier“",
      "summary": "Staatssekretär Lösel hat in Brüssel Landessiegerinnen und Landessieger des Wettbewerbs geehrt.",
      "source_name": "Hessische Landesregierung Presse",
      "source_url": "https://www.hessen.de/presse/hessen-setzt-auf-die-foerderung-junger-forschungs-talente-und-wissenschaftliche-neugier",
      "source_family": "official_state",
      "city": "Hessen",
      "topic": "Politics",
      "published_date": "2026-06-24",
      "summary_status": "html_adapter_minimal",
      "image_rights_status": "placeholder_default",
      "media_type": "placeholder",
      "media_url": null,
      "media_source": "local_placeholder",
      "media_rights_status": "placeholder_default",
      "image_download_allowed": false,
      "youtube_embed_allowed": true
    },
    {
      "item_id": "hessen-government-presse-64-guetesiegel-fuer-familienfreundliche-arbeitgeber-und-hochschulen-verliehen",
      "title": "64 Gütesiegel für familienfreundliche Arbeitgeber und Hochschulen verliehen",
      "summary": "Geehrt wurden 46 Landesdienststellen, eine Hochschule und 17 Kommunen.",
      "source_name": "Hessische Landesregierung Presse",
      "source_url": "https://www.hessen.de/presse/64-guetesiegel-fuer-familienfreundliche-arbeitgeber-und-hochschulen-verliehen",
      "source_family": "official_state",
      "city": "Hessen",
      "topic": "Politics",
      "published_date": "2026-06-24",
      "summary_status": "html_adapter_minimal",
      "image_rights_status": "placeholder_default",
      "media_type": "placeholder",
      "media_url": null,
      "media_source": "local_placeholder",
      "media_rights_status": "placeholder_default",
      "image_download_allowed": false,
      "youtube_embed_allowed": true
    },
    {
      "item_id": "hessen-government-presse-400-meter-mindestabstand-wird-aufgehoben",
      "title": "400 Meter Mindestabstand wird aufgehoben",
      "summary": "Wirtschaftsminister Mansoori: „Wer bezahlbaren Wohnraum schaffen will, muss Bauen einfacher machen. Wir wollen, dass mehr gebaut werden kann.“",
      "source_name": "Hessische Landesregierung Presse",
      "source_url": "https://www.hessen.de/presse/400-meter-mindestabstand-wird-aufgehoben",
      "source_family": "official_state",
      "city": "Hessen",
      "topic": "Politics",
      "published_date": "2026-06-24",
      "summary_status": "html_adapter_minimal",
      "image_rights_status": "placeholder_default",
      "media_type": "placeholder",
      "media_url": null,
      "media_source": "local_placeholder",
      "media_rights_status": "placeholder_default",
      "image_download_allowed": false,
      "youtube_embed_allowed": true
    }
  ]
}